filebrowser/__init__.py
filebrowser/app.py
filebrowser/auth.py
filebrowser/funcs.py
filebrowser/main.py
filebrowser/static/css/file.css
filebrowser/static/css/file1.css
filebrowser/static/fonts/MaterialIcons-Regular.570eb838.woff2
filebrowser/static/js/main.js
filebrowser/templates/data.html
filebrowser/templates/index.html
filebrowser-1.2.0.dist-info/LICENSE
filebrowser-1.2.0.dist-info/METADATA
filebrowser-1.2.0.dist-info/WHEEL
filebrowser-1.2.0.dist-info/entry_points.txt
filebrowser-1.2.0.dist-info/top_level.txt
filebrowser-1.2.0.dist-info/RECORD
