Metadata-Version: 2.1
Name: filebrowser
Version: 1.2.0
Summary: Simple web file browser
Home-page: https://github.com/jakbin/filebrowser
Author: jakbin
License: MIT License
Keywords: filebrowser,web,file,browser,web browser
Platform: any
Classifier: Development Status :: 4 - Beta
Classifier: License :: OSI Approved :: MIT License
Classifier: Operating System :: OS Independent
Classifier: Programming Language :: Python
Classifier: Programming Language :: Python :: 3
License-File: LICENSE
Requires-Dist: flask <=2.0
